Metadata-Version: 1.1
Name: django-popupcrud
Version: 0.8.0
Summary: A CRUD framework that uses HTML popups for CRUD operations.
Home-page: https://github.com/harikvpy/django-popupcrud
Author: Hari Mahadevan
Author-email: hari@smallpearl.com
License: BSD 3-Clause License
Keywords: django-popupcrud
Platform: UNKNOWN
Classifier: Development Status :: 3 - Alpha
Classifier: Intended Audience :: Developers
Classifier: License :: OSI Approved :: MIT License
Classifier: Operating System :: OS Independent
Classifier: Programming Language :: Python :: 2
Classifier: Programming Language :: Python :: 2.7
Classifier: Programming Language :: Python :: 3
Classifier: Programming Language :: Python :: 3.4
Classifier: Topic :: Software Development :: Libraries
Classifier: Environment :: Web Environment
Classifier: Framework :: Django
